Metadata-Version: 2.1
Name: mediapipe-rpi4
Version: 0.8.8
Summary: MediaPipe for Raspberry Pi OS on Raspberry Pi 4
Home-page: https://github.com/superuser789/MediaPipe-on-RaspberryPi
Author: Nitin Singh
Author-email: acc4nitin@gmail.com
License: MIT
Platform: UNKNOWN
Classifier: License :: OSI Approved :: MIT License
Classifier: Programming Language :: Python :: 3
Classifier: Programming Language :: Python :: 3.7
